bencode/BTL.py
bencode/__init__.py
bencode/exceptions.py
bencodepy/__init__.py
bencodepy/common.py
bencodepy/compat.py
bencodepy/decoder.py
bencodepy/encoder.py
bencodepy/exceptions.py
bencode.py-4.0.0.dist-info/AUTHORS
bencode.py-4.0.0.dist-info/AUTHORS.in
bencode.py-4.0.0.dist-info/LICENSE
bencode.py-4.0.0.dist-info/METADATA
bencode.py-4.0.0.dist-info/WHEEL
bencode.py-4.0.0.dist-info/pbr.json
bencode.py-4.0.0.dist-info/top_level.txt
bencode.py-4.0.0.dist-info/RECORD
