Metadata-Version: 1.1
Name: bencode.py
Version: 4.0.0
Summary: Simple bencode parser (for Python 2, Python 3 and PyPy)
Home-page: https://github.com/fuzeman/bencode.py
Author: Dean Gardiner
Author-email: me@dgardiner.net
License: BitTorrent Open Source License
Keywords: bittorrent,bencode,bdecode
Platform: UNKNOWN
Classifier: Development Status :: 5 - Production/Stable
Classifier: Intended Audience :: Developers
Classifier: License :: Other/Proprietary License
Classifier: Operating System :: OS Independent
Classifier: Programming Language :: Python
Classifier: Programming Language :: Python :: 2
Classifier: Programming Language :: Python :: 2.7
Classifier: Programming Language :: Python :: 3
Classifier: Programming Language :: Python :: 3.5
Classifier: Programming Language :: Python :: 3.6
Classifier: Programming Language :: Python :: 3.7
Classifier: Programming Language :: Python :: Implementation :: PyPy
Classifier: Topic :: Software Development :: Libraries
